midterm/AStar.py
midterm/A_star.py
midterm/BFS.py
midterm/DFS.py
midterm/HillClimbing.py
midterm/IDDFS.py
midterm/LAB4DFS.py
midterm/LAB5IDDFS.py
midterm/LAB6UCS.py
midterm/UCS.py
midterm/__init__.py
midterm/algos.py
midterm/astar_b.py
midterm/hc.py
midterm/lab4_activity1.py
midterm/lab4_task1.py
midterm/lab4_task2.py
midterm/lab5_labtask1.py
midterm/lab5_labtask2.py
midterm/lab6_labtask1.py
midterm/lab_activities3.py
midterm/lab_task1.py
midterm/lab_task2.py
midlab-0.5.0.dist-info/LICENSE
midlab-0.5.0.dist-info/METADATA
midlab-0.5.0.dist-info/WHEEL
midlab-0.5.0.dist-info/top_level.txt
midlab-0.5.0.dist-info/RECORD
