Metadata-Version: 2.1
Name: midlab
Version: 0.5.0
Summary: For Lab
Home-page: https://github.com/MalikTalha03/midlab
Author: Malik Talha
Author-email: mtnaqshbandi2003@gmail.com
License: MIT
Classifier: Programming Language :: Python :: 3
Classifier: License :: OSI Approved :: MIT License
Classifier: Operating System :: OS Independent
Requires-Python: >=3.6
License-File: LICENSE
